Andreani_QA_Scanner/__init__.py
Andreani_QA_Scanner/main.py
Andreani_QA_Scanner/app/Axe.js
Andreani_QA_Scanner/app/Downloader.py
Andreani_QA_Scanner/app/Highlight.js
Andreani_QA_Scanner/app/Inspector.js
Andreani_QA_Scanner/app/Monkey.js
Andreani_QA_Scanner/app/Scanner.py
Andreani_QA_Scanner/app/Scraper.js
Andreani_QA_Scanner/app/ScreenManagement.py
Andreani_QA_Scanner/app/ScriptToFile.py
Andreani_QA_Scanner/app/UserManagement.py
Andreani_QA_Scanner/app/__init__.py
Andreani_QA_Scanner/app/extension/Axe.js
Andreani_QA_Scanner/app/extension/Axe.min.js
Andreani_QA_Scanner/app/extension/Pybot_Logo.svg
Andreani_QA_Scanner/app/extension/Recorder.js
Andreani_QA_Scanner/app/extension/Scraper.js
Andreani_QA_Scanner/app/extension/Utils.js
Andreani_QA_Scanner/app/extension/active-64.png
Andreani_QA_Scanner/app/extension/background.js
Andreani_QA_Scanner/app/extension/html2canvas.min.js
Andreani_QA_Scanner/app/extension/logo_pybot.png
Andreani_QA_Scanner/app/extension/manifest.json
Andreani_QA_Scanner/app/extension/popup.html
Andreani_QA_Scanner/app/src/InfractionTranslation.json
Andreani_QA_Scanner/services/Listener.py
Andreani_QA_Scanner/services/__init__.py
Andreani_QA_Scanner/src/__init__.py
Andreani_QA_Scanner/src/index.js
Andreani_QA_Scanner/src/js/__init__.py
Andreani_QA_Scanner/src/js/materialize.js
Andreani_QA_Scanner/src/js/materialize.min.js
Andreani_QA_Scanner/src/js/updateLanding.js
Andreani_QA_Scanner/src/js/updateLauncher.js
Andreani_QA_Scanner/src/js/updateUser.js
Andreani_QA_Scanner/src/style/__init__.py
Andreani_QA_Scanner/src/style/customazer.css
Andreani_QA_Scanner/src/style/materialize.css
Andreani_QA_Scanner/src/style/materialize.min.css
Andreani_QA_Scanner/src/templates/JiraUserConfigs.html
Andreani_QA_Scanner/src/templates/Landing.html
Andreani_QA_Scanner/src/templates/Launcher.html
Andreani_QA_Scanner/src/templates/ReportDefects.html
Andreani_QA_Scanner/src/templates/__init__.py
Andreani_QA_Scanner/views/Landing.py
Andreani_QA_Scanner/views/Launcher.py
Andreani_QA_Scanner-0.0.14.dist-info/METADATA
Andreani_QA_Scanner-0.0.14.dist-info/WHEEL
Andreani_QA_Scanner-0.0.14.dist-info/top_level.txt
Andreani_QA_Scanner-0.0.14.dist-info/RECORD
