Metadata-Version: 2.1
Name: Andreani-QA-Scanner
Version: 0.0.14
Summary: SeleniumFramework para ejecución de casos automatizados
Home-page: UNKNOWN
Author: AndreaniTesting
Author-email: user_appglatest@andreani.com
License: MIT
Platform: UNKNOWN
Requires-Dist: attrs ==23.1.0
Requires-Dist: blinker ==1.7.0
Requires-Dist: bottle ==0.12.25
Requires-Dist: certifi ==2023.7.22
Requires-Dist: cffi ==1.15.1
Requires-Dist: charset-normalizer ==3.3.1
Requires-Dist: click ==8.1.7
Requires-Dist: clr-loader ==0.2.6
Requires-Dist: colorama ==0.4.6
Requires-Dist: exceptiongroup ==1.1.3
Requires-Dist: Flask ==3.0.0
Requires-Dist: h11 ==0.14.0
Requires-Dist: idna ==3.4
Requires-Dist: importlib-metadata ==6.8.0
Requires-Dist: itsdangerous ==2.1.2
Requires-Dist: Jinja2 ==3.1.2
Requires-Dist: libretranslatepy ==2.1.1
Requires-Dist: lxml ==4.9.3
Requires-Dist: MarkupSafe ==2.1.3
Requires-Dist: mtranslate ==1.8
Requires-Dist: outcome ==1.2.0
Requires-Dist: proxy-tools ==0.1.0
Requires-Dist: pycparser ==2.21
Requires-Dist: pyperclip ==1.8.2
Requires-Dist: PySocks ==1.7.1
Requires-Dist: pythonnet ==3.0.1
Requires-Dist: pywebview ==4.3.3
Requires-Dist: requests ==2.31.0
Requires-Dist: screeninfo ==0.8.1
Requires-Dist: selenium ==4.11.2
Requires-Dist: sniffio ==1.3.0
Requires-Dist: sortedcontainers ==2.4.0
Requires-Dist: trio ==0.22.2
Requires-Dist: trio-websocket ==0.10.3
Requires-Dist: typing-extensions ==4.7.1
Requires-Dist: urllib3 ==2.0.4
Requires-Dist: Werkzeug ==3.0.1
Requires-Dist: wsproto ==1.2.0
Requires-Dist: zipp ==3.17.0
Requires-Dist: pynput ==1.7.6
Requires-Dist: flask-cors ==4.0.0
Requires-Dist: openpyxl ==3.1.2
Requires-Dist: tldextract ==5.1.1
Requires-Dist: pillow ==10.2.0
Requires-Dist: python-docx
